fitsdb-0.0.4.dist-info/METADATA
fitsdb-0.0.4.dist-info/WHEEL
fitsdb-0.0.4.dist-info/entry_points.txt
fitsdb/__init__.py
fitsdb/api.py
fitsdb/core.py
fitsdb/db.py
fitsdb/main.py
fitsdb/sqlite.sql
fitsdb-0.0.4.dist-info/RECORD
