Metadata-Version: 2.1
Name: fitsdb
Version: 0.0.4
Summary: Raw FITS database management tool
License: MIT
Requires-Python: >=3.10
Requires-Dist: astropy
Requires-Dist: ipykernel
Requires-Dist: tqdm
Requires-Dist: pyyaml
Requires-Dist: pandas
Requires-Dist: fastapi[standard]
Provides-Extra: test
Requires-Dist: pytest; extra == "test"
Requires-Dist: jaxoplanet>=0.1.0; extra == "test"
Requires-Dist: pytest-xdist; extra == "test"
Provides-Extra: dev
Requires-Dist: ruff; extra == "dev"
Requires-Dist: black; extra == "dev"
Requires-Dist: isort; extra == "dev"
